Metadata-Version: 1.0
Name: s2a-nightly
Version: 0.8.0.dev20191111
Summary: seq2annotation
Home-page: https://github.com/howl-anderson/seq2annotation
Author: Xiaoquan Kong
Author-email: u1mail2me@gmail.com
License: Apache 2.0
Platform: UNKNOWN
